goals/__init__.py
goals/app.py
gui_goals_app-1.0.dist-info/entry_points.txt
gui_goals_app-1.0.dist-info/METADATA
gui_goals_app-1.0.dist-info/WHEEL
gui_goals_app-1.0.dist-info/RECORD
