Metadata-Version: 2.3
Name: gui-goals-app
Version: 1.0
Summary: Script to create, list, mark and delete your goals
Author: Guilherme-ca-trindade
Requires-Python: >=3.12
Classifier: Programming Language :: Python :: 3
Classifier: Programming Language :: Python :: 3.12
Classifier: Programming Language :: Python :: 3.13
Requires-Dist: emoji (>=2.14.1,<3.0.0)
Requires-Dist: questionary (>=2.1.0,<3.0.0)
